Metadata-Version: 2.1
Name: VEnCode
Version: 1.2.0
Summary: Package to get VEnCodes as in Macedo and Gontijo, 2019
Home-page: https://github.com/AndreMacedo88/VEnCode
Author: André Macedo and Alisson M. Gontijo
Author-email: andre.lopes.macedo@gmail.com
License: UNKNOWN
Platform: UNKNOWN
Classifier: Programming Language :: Python :: 3.6
Classifier: Programming Language :: Python :: 3.7
Classifier: Programming Language :: Python :: 3.8
Classifier: License :: OSI Approved :: BSD License
Classifier: Operating System :: OS Independent
Requires-Dist: biopython
Requires-Dist: tqdm
Requires-Dist: numpy
Requires-Dist: pandas
Requires-Dist: matplotlib
Requires-Dist: scipy
